TikTokLive/__init__.py
TikTokLive/utilities.py
TikTokLive/client/__init__.py
TikTokLive/client/base.py
TikTokLive/client/client.py
TikTokLive/client/config.py
TikTokLive/client/httpx.py
TikTokLive/client/wsclient.py
TikTokLive/proto/__init__.py
TikTokLive/proto/tiktok_schema_pb2.py
TikTokLive/proto/utilities.py
TikTokLive/types/__init__.py
TikTokLive/types/errors.py
TikTokLive/types/events.py
TikTokLive/types/objects.py
TikTokLive/types/utilities.py
TikTokLiveClone/__init__.py
TikTokLiveClone/utilities.py
TikTokLiveClone/client/__init__.py
TikTokLiveClone/client/base.py
TikTokLiveClone/client/client.py
TikTokLiveClone/client/config.py
TikTokLiveClone/client/httpx.py
TikTokLiveClone/client/wsclient.py
TikTokLiveClone/proto/__init__.py
TikTokLiveClone/proto/tiktok_schema_pb2.py
TikTokLiveClone/proto/utilities.py
TikTokLiveClone/types/__init__.py
TikTokLiveClone/types/errors.py
TikTokLiveClone/types/events.py
TikTokLiveClone/types/objects.py
TikTokLiveClone/types/utilities.py
TikTokLiveClone-1.0.1.dist-info/LICENSE
TikTokLiveClone-1.0.1.dist-info/METADATA
TikTokLiveClone-1.0.1.dist-info/WHEEL
TikTokLiveClone-1.0.1.dist-info/top_level.txt
TikTokLiveClone-1.0.1.dist-info/RECORD
